{"frames": [

{
	"filename": "bedcrab_idle1.png",
	"frame": {"x":406,"y":232,"w":103,"h":76},
	"rotated": false,
	"trimmed": true,
	"spriteSourceSize": {"x":1,"y":1,"w":103,"h":76},
	"sourceSize": {"w":104,"h":78}
},
{
	"filename": "bedcrab_idle2.png",
	"frame": {"x":406,"y":232,"w":103,"h":76},
	"rotated": false,
	"trimmed": true,
	"spriteSourceSize": {"x":1,"y":1,"w":103,"h":76},
	"sourceSize": {"w":104,"h":78}
},
{
	"filename": "bedcrab_idle3.png",
	"frame": {"x":407,"y":310,"w":103,"h":76},
	"rotated": false,
	"trimmed": true,
	"spriteSourceSize": {"x":1,"y":1,"w":103,"h":76},
	"sourceSize": {"w":105,"h":78}
},
{
	"filename": "bedcrab_idle4.png",
	"frame": {"x":407,"y":310,"w":103,"h":76},
	"rotated": false,
	"trimmed": true,
	"spriteSourceSize": {"x":1,"y":1,"w":103,"h":76},
	"sourceSize": {"w":105,"h":78}
},
{
	"filename": "bedcrab_idle5.png",
	"frame": {"x":406,"y":388,"w":105,"h":76},
	"rotated": false,
	"trimmed": true,
	"spriteSourceSize": {"x":1,"y":1,"w":105,"h":76},
	"sourceSize": {"w":107,"h":78}
},
{
	"filename": "bedcrab_idle6.png",
	"frame": {"x":406,"y":388,"w":105,"h":76},
	"rotated": false,
	"trimmed": true,
	"spriteSourceSize": {"x":1,"y":1,"w":105,"h":76},
	"sourceSize": {"w":107,"h":78}
},
{
	"filename": "bedcrab_idle7.png",
	"frame": {"x":332,"y":1359,"w":107,"h":77},
	"rotated": false,
	"trimmed": true,
	"spriteSourceSize": {"x":1,"y":0,"w":107,"h":77},
	"sourceSize": {"w":109,"h":78}
},
{
	"filename": "bedcrab_idle8.png",
	"frame": {"x":332,"y":1359,"w":107,"h":77},
	"rotated": false,
	"trimmed": true,
	"spriteSourceSize": {"x":1,"y":0,"w":107,"h":77},
	"sourceSize": {"w":109,"h":78}
},
{
	"filename": "bedcrab_idle9.png",
	"frame": {"x":271,"y":1281,"w":110,"h":76},
	"rotated": false,
	"trimmed": true,
	"spriteSourceSize": {"x":1,"y":1,"w":110,"h":76},
	"sourceSize": {"w":112,"h":78}
},
{
	"filename": "bedcrab_idle10.png",
	"frame": {"x":271,"y":1281,"w":110,"h":76},
	"rotated": false,
	"trimmed": true,
	"spriteSourceSize": {"x":1,"y":1,"w":110,"h":76},
	"sourceSize": {"w":112,"h":78}
},
{
	"filename": "bedcrab_idle11.png",
	"frame": {"x":383,"y":1281,"w":110,"h":76},
	"rotated": false,
	"trimmed": true,
	"spriteSourceSize": {"x":1,"y":1,"w":110,"h":76},
	"sourceSize": {"w":112,"h":78}
},
{
	"filename": "bedcrab_idle12.png",
	"frame": {"x":383,"y":1281,"w":110,"h":76},
	"rotated": false,
	"trimmed": true,
	"spriteSourceSize": {"x":1,"y":1,"w":110,"h":76},
	"sourceSize": {"w":112,"h":78}
},
{
	"filename": "bedcrab_idle13.png",
	"frame": {"x":1,"y":1336,"w":110,"h":76},
	"rotated": false,
	"trimmed": true,
	"spriteSourceSize": {"x":1,"y":1,"w":110,"h":76},
	"sourceSize": {"w":112,"h":78}
},
{
	"filename": "bedcrab_idle14.png",
	"frame": {"x":1,"y":1336,"w":110,"h":76},
	"rotated": false,
	"trimmed": true,
	"spriteSourceSize": {"x":1,"y":1,"w":110,"h":76},
	"sourceSize": {"w":112,"h":78}
},
{
	"filename": "bedcrab_idle15.png",
	"frame": {"x":113,"y":1338,"w":109,"h":76},
	"rotated": false,
	"trimmed": true,
	"spriteSourceSize": {"x":1,"y":1,"w":109,"h":76},
	"sourceSize": {"w":111,"h":78}
},
{
	"filename": "bedcrab_idle16.png",
	"frame": {"x":113,"y":1338,"w":109,"h":76},
	"rotated": false,
	"trimmed": true,
	"spriteSourceSize": {"x":1,"y":1,"w":109,"h":76},
	"sourceSize": {"w":111,"h":78}
},
{
	"filename": "bedcrab_idle17.png",
	"frame": {"x":224,"y":1359,"w":106,"h":76},
	"rotated": false,
	"trimmed": true,
	"spriteSourceSize": {"x":1,"y":0,"w":106,"h":76},
	"sourceSize": {"w":108,"h":77}
},
{
	"filename": "bedcrab_idle18.png",
	"frame": {"x":224,"y":1359,"w":106,"h":76},
	"rotated": false,
	"trimmed": true,
	"spriteSourceSize": {"x":1,"y":0,"w":106,"h":76},
	"sourceSize": {"w":108,"h":77}
},
{
	"filename": "bedcrab_idle19.png",
	"frame": {"x":406,"y":78,"w":105,"h":75},
	"rotated": false,
	"trimmed": true,
	"spriteSourceSize": {"x":1,"y":1,"w":105,"h":75},
	"sourceSize": {"w":107,"h":77}
},
{
	"filename": "bedcrab_idle20.png",
	"frame": {"x":406,"y":78,"w":105,"h":75},
	"rotated": false,
	"trimmed": true,
	"spriteSourceSize": {"x":1,"y":1,"w":105,"h":75},
	"sourceSize": {"w":107,"h":77}
},
{
	"filename": "bedcrab_idle21.png",
	"frame": {"x":408,"y":155,"w":103,"h":75},
	"rotated": false,
	"trimmed": true,
	"spriteSourceSize": {"x":1,"y":1,"w":103,"h":75},
	"sourceSize": {"w":105,"h":77}
},
{
	"filename": "bedcrab_idle22.png",
	"frame": {"x":408,"y":155,"w":103,"h":75},
	"rotated": false,
	"trimmed": true,
	"spriteSourceSize": {"x":1,"y":1,"w":103,"h":75},
	"sourceSize": {"w":105,"h":77}
},
{
	"filename": "bedcrab_idle23.png",
	"frame": {"x":406,"y":232,"w":103,"h":76},
	"rotated": false,
	"trimmed": true,
	"spriteSourceSize": {"x":1,"y":1,"w":103,"h":76},
	"sourceSize": {"w":104,"h":78}
},
{
	"filename": "bedcrab_idle24.png",
	"frame": {"x":406,"y":232,"w":103,"h":76},
	"rotated": false,
	"trimmed": true,
	"spriteSourceSize": {"x":1,"y":1,"w":103,"h":76},
	"sourceSize": {"w":104,"h":78}
},
{
	"filename": "bedcrab_idle25.png",
	"frame": {"x":406,"y":232,"w":103,"h":76},
	"rotated": false,
	"trimmed": true,
	"spriteSourceSize": {"x":1,"y":1,"w":103,"h":76},
	"sourceSize": {"w":104,"h":78}
},
{
	"filename": "bedcrab_idle26.png",
	"frame": {"x":406,"y":232,"w":103,"h":76},
	"rotated": false,
	"trimmed": true,
	"spriteSourceSize": {"x":1,"y":1,"w":103,"h":76},
	"sourceSize": {"w":104,"h":78}
},
{
	"filename": "bedcrab_idle27.png",
	"frame": {"x":406,"y":232,"w":103,"h":76},
	"rotated": false,
	"trimmed": true,
	"spriteSourceSize": {"x":1,"y":1,"w":103,"h":76},
	"sourceSize": {"w":104,"h":78}
},
{
	"filename": "bedcrab_sad1.png",
	"frame": {"x":136,"y":1042,"w":133,"h":57},
	"rotated": false,
	"trimmed": true,
	"spriteSourceSize": {"x":0,"y":1,"w":133,"h":57},
	"sourceSize": {"w":134,"h":59}
},
{
	"filename": "bedcrab_sad2.png",
	"frame": {"x":271,"y":1221,"w":133,"h":58},
	"rotated": false,
	"trimmed": true,
	"spriteSourceSize": {"x":1,"y":1,"w":133,"h":58},
	"sourceSize": {"w":135,"h":59}
},
{
	"filename": "bedcrab_sad3.png",
	"frame": {"x":271,"y":1044,"w":133,"h":57},
	"rotated": false,
	"trimmed": true,
	"spriteSourceSize": {"x":1,"y":1,"w":133,"h":57},
	"sourceSize": {"w":135,"h":59}
},
{
	"filename": "bedcrab_sad4.png",
	"frame": {"x":1,"y":1099,"w":133,"h":57},
	"rotated": false,
	"trimmed": true,
	"spriteSourceSize": {"x":1,"y":1,"w":133,"h":57},
	"sourceSize": {"w":135,"h":59}
},
{
	"filename": "bedcrab_sad5.png",
	"frame": {"x":136,"y":1101,"w":133,"h":57},
	"rotated": false,
	"trimmed": true,
	"spriteSourceSize": {"x":1,"y":1,"w":133,"h":57},
	"sourceSize": {"w":135,"h":59}
},
{
	"filename": "bedcrab_sad6.png",
	"frame": {"x":1,"y":1276,"w":133,"h":58},
	"rotated": false,
	"trimmed": true,
	"spriteSourceSize": {"x":0,"y":1,"w":133,"h":58},
	"sourceSize": {"w":134,"h":59}
},
{
	"filename": "bedcrab_sad7.png",
	"frame": {"x":271,"y":986,"w":133,"h":56},
	"rotated": false,
	"trimmed": true,
	"spriteSourceSize": {"x":1,"y":1,"w":133,"h":56},
	"sourceSize": {"w":134,"h":58}
},
{
	"filename": "bedcrab_sad8.png",
	"frame": {"x":1,"y":1041,"w":133,"h":56},
	"rotated": false,
	"trimmed": true,
	"spriteSourceSize": {"x":1,"y":1,"w":133,"h":56},
	"sourceSize": {"w":134,"h":58}
},
{
	"filename": "bedcrab_sad9.png",
	"frame": {"x":136,"y":1219,"w":133,"h":57},
	"rotated": false,
	"trimmed": true,
	"spriteSourceSize": {"x":1,"y":1,"w":133,"h":57},
	"sourceSize": {"w":134,"h":58}
},
{
	"filename": "bedcrab_sad10.png",
	"frame": {"x":271,"y":812,"w":133,"h":56},
	"rotated": false,
	"trimmed": true,
	"spriteSourceSize": {"x":0,"y":1,"w":133,"h":56},
	"sourceSize": {"w":134,"h":58}
},
{
	"filename": "bedcrab_sad11.png",
	"frame": {"x":1,"y":867,"w":133,"h":56},
	"rotated": false,
	"trimmed": true,
	"spriteSourceSize": {"x":0,"y":1,"w":133,"h":56},
	"sourceSize": {"w":134,"h":58}
},
{
	"filename": "bedcrab_sad12.png",
	"frame": {"x":1,"y":753,"w":133,"h":55},
	"rotated": false,
	"trimmed": true,
	"spriteSourceSize": {"x":1,"y":1,"w":133,"h":55},
	"sourceSize": {"w":134,"h":57}
},
{
	"filename": "bedcrab_sad13.png",
	"frame": {"x":136,"y":754,"w":133,"h":55},
	"rotated": false,
	"trimmed": true,
	"spriteSourceSize": {"x":1,"y":1,"w":133,"h":55},
	"sourceSize": {"w":134,"h":57}
},
{
	"filename": "bedcrab_sad14.png",
	"frame": {"x":271,"y":755,"w":133,"h":55},
	"rotated": false,
	"trimmed": true,
	"spriteSourceSize": {"x":1,"y":1,"w":133,"h":55},
	"sourceSize": {"w":134,"h":57}
},
{
	"filename": "bedcrab_sad15.png",
	"frame": {"x":1,"y":585,"w":133,"h":54},
	"rotated": false,
	"trimmed": true,
	"spriteSourceSize": {"x":1,"y":1,"w":133,"h":54},
	"sourceSize": {"w":134,"h":56}
},
{
	"filename": "bedcrab_sad16.png",
	"frame": {"x":1,"y":810,"w":133,"h":55},
	"rotated": false,
	"trimmed": true,
	"spriteSourceSize": {"x":1,"y":1,"w":133,"h":55},
	"sourceSize": {"w":134,"h":56}
},
{
	"filename": "bedcrab_sad17.png",
	"frame": {"x":136,"y":586,"w":133,"h":54},
	"rotated": false,
	"trimmed": true,
	"spriteSourceSize": {"x":1,"y":1,"w":133,"h":54},
	"sourceSize": {"w":134,"h":56}
},
{
	"filename": "bedcrab_sad18.png",
	"frame": {"x":271,"y":587,"w":133,"h":54},
	"rotated": false,
	"trimmed": true,
	"spriteSourceSize": {"x":0,"y":1,"w":133,"h":54},
	"sourceSize": {"w":134,"h":56}
},
{
	"filename": "bedcrab_sad19.png",
	"frame": {"x":271,"y":477,"w":134,"h":53},
	"rotated": false,
	"trimmed": true,
	"spriteSourceSize": {"x":0,"y":1,"w":134,"h":53},
	"sourceSize": {"w":134,"h":55}
},
{
	"filename": "bedcrab_sad20.png",
	"frame": {"x":1,"y":475,"w":133,"h":53},
	"rotated": false,
	"trimmed": true,
	"spriteSourceSize": {"x":1,"y":1,"w":133,"h":53},
	"sourceSize": {"w":134,"h":55}
},
{
	"filename": "bedcrab_sad21.png",
	"frame": {"x":136,"y":476,"w":133,"h":53},
	"rotated": false,
	"trimmed": true,
	"spriteSourceSize": {"x":0,"y":1,"w":133,"h":53},
	"sourceSize": {"w":134,"h":55}
},
{
	"filename": "bedcrab_sad22.png",
	"frame": {"x":272,"y":315,"w":133,"h":52},
	"rotated": false,
	"trimmed": true,
	"spriteSourceSize": {"x":1,"y":1,"w":133,"h":52},
	"sourceSize": {"w":134,"h":54}
},
{
	"filename": "bedcrab_sad23.png",
	"frame": {"x":1,"y":367,"w":133,"h":52},
	"rotated": false,
	"trimmed": true,
	"spriteSourceSize": {"x":1,"y":1,"w":133,"h":52},
	"sourceSize": {"w":134,"h":54}
},
{
	"filename": "bedcrab_sad24.png",
	"frame": {"x":136,"y":368,"w":133,"h":52},
	"rotated": false,
	"trimmed": true,
	"spriteSourceSize": {"x":1,"y":1,"w":133,"h":52},
	"sourceSize": {"w":134,"h":54}
},
{
	"filename": "bedcrab_sad25.png",
	"frame": {"x":271,"y":369,"w":133,"h":52},
	"rotated": false,
	"trimmed": true,
	"spriteSourceSize": {"x":1,"y":1,"w":133,"h":52},
	"sourceSize": {"w":134,"h":53}
},
{
	"filename": "bedcrab_sad26.png",
	"frame": {"x":1,"y":530,"w":133,"h":53},
	"rotated": false,
	"trimmed": true,
	"spriteSourceSize": {"x":1,"y":0,"w":133,"h":53},
	"sourceSize": {"w":134,"h":53}
},
{
	"filename": "bedcrab_sad27.png",
	"frame": {"x":136,"y":209,"w":133,"h":51},
	"rotated": false,
	"trimmed": true,
	"spriteSourceSize": {"x":1,"y":1,"w":133,"h":51},
	"sourceSize": {"w":134,"h":53}
},
{
	"filename": "bedcrab_sad28.png",
	"frame": {"x":271,"y":209,"w":133,"h":51},
	"rotated": false,
	"trimmed": true,
	"spriteSourceSize": {"x":1,"y":1,"w":133,"h":51},
	"sourceSize": {"w":134,"h":53}
},
{
	"filename": "bedcrab_sad29.png",
	"frame": {"x":1,"y":261,"w":133,"h":51},
	"rotated": false,
	"trimmed": true,
	"spriteSourceSize": {"x":1,"y":1,"w":133,"h":51},
	"sourceSize": {"w":134,"h":53}
},
{
	"filename": "bedcrab_sad30.png",
	"frame": {"x":1,"y":1,"w":133,"h":50},
	"rotated": false,
	"trimmed": true,
	"spriteSourceSize": {"x":1,"y":1,"w":133,"h":50},
	"sourceSize": {"w":134,"h":52}
},
{
	"filename": "bedcrab_sad31.png",
	"frame": {"x":136,"y":1,"w":133,"h":50},
	"rotated": false,
	"trimmed": true,
	"spriteSourceSize": {"x":1,"y":1,"w":133,"h":50},
	"sourceSize": {"w":134,"h":52}
},
{
	"filename": "bedcrab_sad32.png",
	"frame": {"x":271,"y":1,"w":133,"h":50},
	"rotated": false,
	"trimmed": true,
	"spriteSourceSize": {"x":1,"y":1,"w":133,"h":50},
	"sourceSize": {"w":134,"h":52}
},
{
	"filename": "bedcrab_sad33.png",
	"frame": {"x":1,"y":53,"w":133,"h":50},
	"rotated": false,
	"trimmed": true,
	"spriteSourceSize": {"x":1,"y":1,"w":133,"h":50},
	"sourceSize": {"w":134,"h":52}
},
{
	"filename": "bedcrab_sad34.png",
	"frame": {"x":136,"y":53,"w":133,"h":50},
	"rotated": false,
	"trimmed": true,
	"spriteSourceSize": {"x":1,"y":1,"w":133,"h":50},
	"sourceSize": {"w":134,"h":52}
},
{
	"filename": "bedcrab_sad35.png",
	"frame": {"x":271,"y":53,"w":133,"h":50},
	"rotated": false,
	"trimmed": true,
	"spriteSourceSize": {"x":1,"y":1,"w":133,"h":50},
	"sourceSize": {"w":134,"h":52}
},
{
	"filename": "bedcrab_sad36.png",
	"frame": {"x":1,"y":105,"w":133,"h":50},
	"rotated": false,
	"trimmed": true,
	"spriteSourceSize": {"x":1,"y":1,"w":133,"h":50},
	"sourceSize": {"w":134,"h":52}
},
{
	"filename": "bedcrab_sad37.png",
	"frame": {"x":136,"y":105,"w":133,"h":50},
	"rotated": false,
	"trimmed": true,
	"spriteSourceSize": {"x":1,"y":1,"w":133,"h":50},
	"sourceSize": {"w":134,"h":52}
},
{
	"filename": "bedcrab_sad38.png",
	"frame": {"x":1,"y":157,"w":134,"h":50},
	"rotated": false,
	"trimmed": true,
	"spriteSourceSize": {"x":0,"y":1,"w":134,"h":50},
	"sourceSize": {"w":134,"h":52}
},
{
	"filename": "bedcrab_sad39.png",
	"frame": {"x":137,"y":157,"w":134,"h":50},
	"rotated": false,
	"trimmed": true,
	"spriteSourceSize": {"x":0,"y":1,"w":134,"h":50},
	"sourceSize": {"w":134,"h":52}
},
{
	"filename": "bedcrab_sad40.png",
	"frame": {"x":271,"y":105,"w":133,"h":50},
	"rotated": false,
	"trimmed": true,
	"spriteSourceSize": {"x":1,"y":1,"w":133,"h":50},
	"sourceSize": {"w":134,"h":52}
},
{
	"filename": "bedcrab_sad41.png",
	"frame": {"x":273,"y":157,"w":133,"h":50},
	"rotated": false,
	"trimmed": true,
	"spriteSourceSize": {"x":1,"y":1,"w":133,"h":50},
	"sourceSize": {"w":134,"h":52}
},
{
	"filename": "bedcrab_sad42.png",
	"frame": {"x":1,"y":209,"w":133,"h":50},
	"rotated": false,
	"trimmed": true,
	"spriteSourceSize": {"x":1,"y":1,"w":133,"h":50},
	"sourceSize": {"w":134,"h":52}
},
{
	"filename": "bedcrab_sad43.png",
	"frame": {"x":1,"y":421,"w":133,"h":52},
	"rotated": false,
	"trimmed": true,
	"spriteSourceSize": {"x":1,"y":1,"w":133,"h":52},
	"sourceSize": {"w":134,"h":53}
},
{
	"filename": "bedcrab_sad44.png",
	"frame": {"x":136,"y":262,"w":133,"h":51},
	"rotated": false,
	"trimmed": true,
	"spriteSourceSize": {"x":1,"y":1,"w":133,"h":51},
	"sourceSize": {"w":134,"h":53}
},
{
	"filename": "bedcrab_sad45.png",
	"frame": {"x":271,"y":262,"w":133,"h":51},
	"rotated": false,
	"trimmed": true,
	"spriteSourceSize": {"x":1,"y":1,"w":133,"h":51},
	"sourceSize": {"w":134,"h":53}
},
{
	"filename": "bedcrab_sad46.png",
	"frame": {"x":136,"y":315,"w":134,"h":51},
	"rotated": false,
	"trimmed": true,
	"spriteSourceSize": {"x":0,"y":1,"w":134,"h":51},
	"sourceSize": {"w":134,"h":53}
},
{
	"filename": "bedcrab_sad47.png",
	"frame": {"x":1,"y":314,"w":133,"h":51},
	"rotated": false,
	"trimmed": true,
	"spriteSourceSize": {"x":1,"y":1,"w":133,"h":51},
	"sourceSize": {"w":134,"h":53}
},
{
	"filename": "bedcrab_sad48.png",
	"frame": {"x":136,"y":422,"w":133,"h":52},
	"rotated": false,
	"trimmed": true,
	"spriteSourceSize": {"x":1,"y":1,"w":133,"h":52},
	"sourceSize": {"w":134,"h":54}
},
{
	"filename": "bedcrab_sad49.png",
	"frame": {"x":271,"y":423,"w":133,"h":52},
	"rotated": false,
	"trimmed": true,
	"spriteSourceSize": {"x":1,"y":1,"w":133,"h":52},
	"sourceSize": {"w":134,"h":54}
},
{
	"filename": "bedcrab_sad50.png",
	"frame": {"x":136,"y":531,"w":133,"h":53},
	"rotated": false,
	"trimmed": true,
	"spriteSourceSize": {"x":1,"y":0,"w":133,"h":53},
	"sourceSize": {"w":134,"h":54}
},
{
	"filename": "bedcrab_sad51.png",
	"frame": {"x":1,"y":641,"w":133,"h":54},
	"rotated": false,
	"trimmed": true,
	"spriteSourceSize": {"x":0,"y":1,"w":133,"h":54},
	"sourceSize": {"w":134,"h":55}
},
{
	"filename": "bedcrab_sad52.png",
	"frame": {"x":271,"y":532,"w":133,"h":53},
	"rotated": false,
	"trimmed": true,
	"spriteSourceSize": {"x":1,"y":1,"w":133,"h":53},
	"sourceSize": {"w":134,"h":55}
},
{
	"filename": "bedcrab_sad53.png",
	"frame": {"x":136,"y":643,"w":134,"h":53},
	"rotated": false,
	"trimmed": true,
	"spriteSourceSize": {"x":0,"y":1,"w":134,"h":53},
	"sourceSize": {"w":134,"h":55}
},
{
	"filename": "bedcrab_sad54.png",
	"frame": {"x":272,"y":643,"w":133,"h":54},
	"rotated": false,
	"trimmed": true,
	"spriteSourceSize": {"x":0,"y":1,"w":133,"h":54},
	"sourceSize": {"w":134,"h":56}
},
{
	"filename": "bedcrab_sad55.png",
	"frame": {"x":1,"y":697,"w":133,"h":54},
	"rotated": false,
	"trimmed": true,
	"spriteSourceSize": {"x":1,"y":1,"w":133,"h":54},
	"sourceSize": {"w":134,"h":56}
},
{
	"filename": "bedcrab_sad56.png",
	"frame": {"x":136,"y":698,"w":133,"h":54},
	"rotated": false,
	"trimmed": true,
	"spriteSourceSize": {"x":1,"y":1,"w":133,"h":54},
	"sourceSize": {"w":134,"h":56}
},
{
	"filename": "bedcrab_sad57.png",
	"frame": {"x":271,"y":699,"w":133,"h":54},
	"rotated": false,
	"trimmed": true,
	"spriteSourceSize": {"x":1,"y":1,"w":133,"h":54},
	"sourceSize": {"w":134,"h":56}
},
{
	"filename": "bedcrab_sad58.png",
	"frame": {"x":136,"y":868,"w":133,"h":56},
	"rotated": false,
	"trimmed": true,
	"spriteSourceSize": {"x":0,"y":1,"w":133,"h":56},
	"sourceSize": {"w":134,"h":57}
},
{
	"filename": "bedcrab_sad59.png",
	"frame": {"x":136,"y":811,"w":133,"h":55},
	"rotated": false,
	"trimmed": true,
	"spriteSourceSize": {"x":0,"y":1,"w":133,"h":55},
	"sourceSize": {"w":134,"h":57}
},
{
	"filename": "bedcrab_sad60.png",
	"frame": {"x":271,"y":870,"w":133,"h":56},
	"rotated": false,
	"trimmed": true,
	"spriteSourceSize": {"x":1,"y":1,"w":133,"h":56},
	"sourceSize": {"w":134,"h":57}
},
{
	"filename": "bedcrab_sad61.png",
	"frame": {"x":1,"y":925,"w":133,"h":56},
	"rotated": false,
	"trimmed": true,
	"spriteSourceSize": {"x":0,"y":1,"w":133,"h":56},
	"sourceSize": {"w":134,"h":58}
},
{
	"filename": "bedcrab_sad62.png",
	"frame": {"x":136,"y":926,"w":133,"h":56},
	"rotated": false,
	"trimmed": true,
	"spriteSourceSize": {"x":0,"y":1,"w":133,"h":56},
	"sourceSize": {"w":134,"h":58}
},
{
	"filename": "bedcrab_sad63.png",
	"frame": {"x":271,"y":928,"w":133,"h":56},
	"rotated": false,
	"trimmed": true,
	"spriteSourceSize": {"x":0,"y":1,"w":133,"h":56},
	"sourceSize": {"w":134,"h":58}
},
{
	"filename": "bedcrab_sad64.png",
	"frame": {"x":1,"y":983,"w":133,"h":56},
	"rotated": false,
	"trimmed": true,
	"spriteSourceSize": {"x":1,"y":1,"w":133,"h":56},
	"sourceSize": {"w":134,"h":58}
},
{
	"filename": "bedcrab_sad65.png",
	"frame": {"x":136,"y":984,"w":133,"h":56},
	"rotated": false,
	"trimmed": true,
	"spriteSourceSize": {"x":1,"y":1,"w":133,"h":56},
	"sourceSize": {"w":134,"h":58}
},
{
	"filename": "bedcrab_sad66.png",
	"frame": {"x":271,"y":1103,"w":133,"h":57},
	"rotated": false,
	"trimmed": true,
	"spriteSourceSize": {"x":0,"y":1,"w":133,"h":57},
	"sourceSize": {"w":134,"h":59}
},
{
	"filename": "bedcrab_sad67.png",
	"frame": {"x":1,"y":1158,"w":133,"h":57},
	"rotated": false,
	"trimmed": true,
	"spriteSourceSize": {"x":0,"y":1,"w":133,"h":57},
	"sourceSize": {"w":134,"h":59}
},
{
	"filename": "bedcrab_sad68.png",
	"frame": {"x":136,"y":1160,"w":133,"h":57},
	"rotated": false,
	"trimmed": true,
	"spriteSourceSize": {"x":1,"y":1,"w":133,"h":57},
	"sourceSize": {"w":135,"h":59}
},
{
	"filename": "bedcrab_sad69.png",
	"frame": {"x":271,"y":1162,"w":133,"h":57},
	"rotated": false,
	"trimmed": true,
	"spriteSourceSize": {"x":1,"y":1,"w":133,"h":57},
	"sourceSize": {"w":135,"h":59}
},
{
	"filename": "bedcrab_sad70.png",
	"frame": {"x":1,"y":1217,"w":133,"h":57},
	"rotated": false,
	"trimmed": true,
	"spriteSourceSize": {"x":0,"y":1,"w":133,"h":57},
	"sourceSize": {"w":134,"h":59}
},
{
	"filename": "bedcrab_sad71.png",
	"frame": {"x":271,"y":1221,"w":133,"h":58},
	"rotated": false,
	"trimmed": true,
	"spriteSourceSize": {"x":1,"y":1,"w":133,"h":58},
	"sourceSize": {"w":135,"h":59}
},
{
	"filename": "bedcrab_sad72.png",
	"frame": {"x":136,"y":1278,"w":133,"h":58},
	"rotated": false,
	"trimmed": true,
	"spriteSourceSize": {"x":1,"y":1,"w":133,"h":58},
	"sourceSize": {"w":135,"h":59}
},
{
	"filename": "bedcrab_Scared1.png",
	"frame": {"x":406,"y":973,"w":85,"h":88},
	"rotated": false,
	"trimmed": true,
	"spriteSourceSize": {"x":1,"y":1,"w":85,"h":88},
	"sourceSize": {"w":87,"h":90}
},
{
	"filename": "bedcrab_Scared2.png",
	"frame": {"x":406,"y":709,"w":86,"h":86},
	"rotated": false,
	"trimmed": true,
	"spriteSourceSize": {"x":1,"y":0,"w":86,"h":86},
	"sourceSize": {"w":88,"h":86}
},
{
	"filename": "bedcrab_Scared3.png",
	"frame": {"x":406,"y":797,"w":88,"h":86},
	"rotated": false,
	"trimmed": true,
	"spriteSourceSize": {"x":1,"y":1,"w":88,"h":86},
	"sourceSize": {"w":90,"h":88}
},
{
	"filename": "bedcrab_Scared4.png",
	"frame": {"x":406,"y":1063,"w":86,"h":90},
	"rotated": false,
	"trimmed": true,
	"spriteSourceSize": {"x":1,"y":1,"w":86,"h":90},
	"sourceSize": {"w":88,"h":92}
},
{
	"filename": "bedcrab_Scared5.png",
	"frame": {"x":406,"y":885,"w":85,"h":86},
	"rotated": false,
	"trimmed": true,
	"spriteSourceSize": {"x":1,"y":1,"w":85,"h":86},
	"sourceSize": {"w":87,"h":88}
},
{
	"filename": "bedcrab_Walk1.png",
	"frame": {"x":407,"y":466,"w":93,"h":78},
	"rotated": false,
	"trimmed": true,
	"spriteSourceSize": {"x":0,"y":1,"w":93,"h":78},
	"sourceSize": {"w":93,"h":80}
},
{
	"filename": "bedcrab_Walk2.png",
	"frame": {"x":407,"y":466,"w":93,"h":78},
	"rotated": false,
	"trimmed": true,
	"spriteSourceSize": {"x":0,"y":1,"w":93,"h":78},
	"sourceSize": {"w":93,"h":80}
},
{
	"filename": "bedcrab_Walk3.png",
	"frame": {"x":407,"y":466,"w":93,"h":78},
	"rotated": false,
	"trimmed": true,
	"spriteSourceSize": {"x":0,"y":1,"w":93,"h":78},
	"sourceSize": {"w":93,"h":80}
},
{
	"filename": "bedcrab_Walk4.png",
	"frame": {"x":406,"y":1,"w":92,"h":75},
	"rotated": false,
	"trimmed": true,
	"spriteSourceSize": {"x":1,"y":1,"w":92,"h":75},
	"sourceSize": {"w":93,"h":77}
},
{
	"filename": "bedcrab_Walk5.png",
	"frame": {"x":406,"y":1,"w":92,"h":75},
	"rotated": false,
	"trimmed": true,
	"spriteSourceSize": {"x":1,"y":1,"w":92,"h":75},
	"sourceSize": {"w":93,"h":77}
},
{
	"filename": "bedcrab_Walk6.png",
	"frame": {"x":406,"y":1,"w":92,"h":75},
	"rotated": false,
	"trimmed": true,
	"spriteSourceSize": {"x":1,"y":1,"w":92,"h":75},
	"sourceSize": {"w":93,"h":77}
},
{
	"filename": "bedcrab_Walk7.png",
	"frame": {"x":406,"y":546,"w":92,"h":79},
	"rotated": false,
	"trimmed": true,
	"spriteSourceSize": {"x":1,"y":1,"w":92,"h":79},
	"sourceSize": {"w":94,"h":81}
},
{
	"filename": "bedcrab_Walk8.png",
	"frame": {"x":406,"y":546,"w":92,"h":79},
	"rotated": false,
	"trimmed": true,
	"spriteSourceSize": {"x":1,"y":1,"w":92,"h":79},
	"sourceSize": {"w":94,"h":81}
},
{
	"filename": "bedcrab_Walk9.png",
	"frame": {"x":406,"y":546,"w":92,"h":79},
	"rotated": false,
	"trimmed": true,
	"spriteSourceSize": {"x":1,"y":1,"w":92,"h":79},
	"sourceSize": {"w":94,"h":81}
},
{
	"filename": "bedcrab_Walk10.png",
	"frame": {"x":407,"y":627,"w":89,"h":80},
	"rotated": false,
	"trimmed": true,
	"spriteSourceSize": {"x":1,"y":1,"w":89,"h":80},
	"sourceSize": {"w":90,"h":82}
},
{
	"filename": "bedcrab_Walk11.png",
	"frame": {"x":407,"y":627,"w":89,"h":80},
	"rotated": false,
	"trimmed": true,
	"spriteSourceSize": {"x":1,"y":1,"w":89,"h":80},
	"sourceSize": {"w":90,"h":82}
},
{
	"filename": "bedcrab_Walk12.png",
	"frame": {"x":407,"y":627,"w":89,"h":80},
	"rotated": false,
	"trimmed": true,
	"spriteSourceSize": {"x":1,"y":1,"w":89,"h":80},
	"sourceSize": {"w":90,"h":82}
}],
"meta": {
	"app": "https://www.codeandweb.com/texturepacker",
	"version": "1.0",
	"image": "bedcrab.png",
	"format": "RGBA8888",
	"size": {"w":512,"h":1437},
	"scale": "1",
	"smartupdate": "$TexturePacker:SmartUpdate:2fcab815b6c9ae8143e02ae85584a26b:b4b495695ce375b80aad0f813265c915:eb627b4390611a0248144def707f8653$"
}
}
